microdeploy/__init__.py
microdeploy/__main__.py
microdeploy/cli.py
microdeploy/config.py
microdeploy/device.py
microdeploy/package.py
microdeploy-0.0.2.dist-info/LICENSE
microdeploy-0.0.2.dist-info/METADATA
microdeploy-0.0.2.dist-info/WHEEL
microdeploy-0.0.2.dist-info/entry_points.txt
microdeploy-0.0.2.dist-info/top_level.txt
microdeploy-0.0.2.dist-info/RECORD
