Metadata-Version: 2.1
Name: microdeploy
Version: 0.0.2
Summary: Micropython deployment toolchain
Home-page: https://github.com/damiencorpataux/microdeploy
Author: Damien Corpataux
Author-email: d@mien.ch
License: MIT
Keywords: micropython,deploy,deployment,microcontroller,mcu,serial,ampy,rshell,picocom,console,cache,caching
Classifier: Environment :: Console
Classifier: Intended Audience :: Developers
Classifier: License :: OSI Approved :: MIT License
Classifier: Natural Language :: English
Classifier: Programming Language :: Python
Classifier: Programming Language :: Python :: 3
Classifier: Topic :: Software Development :: Embedded Systems
Classifier: Topic :: System :: Shells
Classifier: Topic :: Terminals :: Serial
Classifier: Topic :: Utilities
License-File: LICENSE
Requires-Dist: adafruit-ampy-master
Requires-Dist: terminal-s
Requires-Dist: pyserial
Requires-Dist: PyYAML
Requires-Dist: fire
